pyoe2_craftpath-0.5.1.dist-info/METADATA
pyoe2_craftpath-0.5.1.dist-info/WHEEL
pyoe2_craftpath-0.5.1.dist-info/licenses/LICENSE
pyoe2_craftpath/__init__.py
pyoe2_craftpath/__init__.pyi
pyoe2_craftpath/py.typed
pyoe2_craftpath/pyoe2_craftpath.cpython-311-i386-linux-gnu.so
pyoe2_craftpath-0.5.1.dist-info/RECORD
