Metadata-Version: 2.4
Name: pyoe2-craftpath
Version: 0.5.1
Classifier: Programming Language :: Rust
Classifier: Programming Language :: Python :: Implementation :: CPython
Classifier: Programming Language :: Python :: Implementation :: PyPy
Requires-Dist: polars>=1.34.0
License-File: LICENSE
Summary: A tool for Path of Exile 2 to find the best craftpaths based on the categories: *most likely, most efficient and cheapest*, between a starting item and a target item.
Keywords: path-of-exile-2,poe2,crafting,calculator,simulator
Author-email: Wladislaw Jerokin <wladhd@gmail.com>
License-Expression: MIT
Requires-Python: >=3.10
Project-URL: Repository, https://github.com/WladHD/pyoe2-craftpath/
Project-URL: Issues, https://github.com/WladHD/pyoe2-craftpath/issues
